PySelenium-1.0.2.dist-info/DESCRIPTION.rst
PySelenium-1.0.2.dist-info/METADATA
PySelenium-1.0.2.dist-info/RECORD
PySelenium-1.0.2.dist-info/WHEEL
PySelenium-1.0.2.dist-info/metadata.json
PySelenium-1.0.2.dist-info/pbr.json
PySelenium-1.0.2.dist-info/top_level.txt
pyselenium/__init__.py
pyselenium/_selenium_wrapper.py
pyselenium/sample_test.py
pyselenium/test_metadata.py
pyselenium/test_runner.py
pyselenium/test_steps.py
