Metadata-Version: 1.1
Name: PySelenium
Version: 1.0.2
Summary: A wrapper for Selenium to allow easy development of automated tests for the web
Home-page: https://github.com/felipefiali/PySelenium
Author: Felipe Fiali de Sá
Author-email: felipefiali@gmail.com
License: MIT License
Download-URL: https://github.com/felipefiali/PySelenium/archive/1.0.2.tar.gz
Keywords: testing,test-automation,selenium,web-automation
Platform: Windows
Platform: Linux
Platform: MacOS
Classifier: License :: OSI Approved :: MIT License
Classifier: Intended Audience :: Developers
Classifier: Development Status :: 5 - Production/Stable
Classifier: Programming Language :: Python
Classifier: Programming Language :: Python :: 3.6
Classifier: Operating System :: MacOS
Classifier: Operating System :: Microsoft :: Windows
Classifier: Operating System :: POSIX :: Linux
Classifier: Operating System :: Unix
Classifier: Topic :: Software Development
Classifier: Topic :: Software Development :: Libraries :: Python Modules
Classifier: Topic :: Software Development :: Quality Assurance
Classifier: Topic :: Software Development :: Testing
Classifier: Topic :: Utilities
